{
  "model_id": "unsloth/Llama-3.1-8B-Instruct",
  "model_key": "llama3.1-8b",
  "domain": "sports",
  "task": "tutor",
  "variant": "strong",
  "lr": 0.0001,
  "lr_default": 0.0003,
  "r": 32,
  "alpha": 64,
  "per_device_bs": 16,
  "grad_accum": 1,
  "effective_bs": 16,
  "epochs": 1,
  "seed": 42,
  "n_train": 4100,
  "n_eval": 400,
  "final_train_loss": 1.4128,
  "loss_history": [
    {
      "step": 5,
      "loss": 2.3799,
      "epoch": 0.019455252918287938
    },
    {
      "step": 10,
      "loss": 1.9438,
      "epoch": 0.038910505836575876
    },
    {
      "step": 15,
      "loss": 1.7682,
      "epoch": 0.058365758754863814
    },
    {
      "step": 20,
      "loss": 1.7285,
      "epoch": 0.07782101167315175
    },
    {
      "step": 25,
      "loss": 1.7343,
      "epoch": 0.09727626459143969
    },
    {
      "step": 30,
      "loss": 1.6793,
      "epoch": 0.11673151750972763
    },
    {
      "step": 35,
      "loss": 1.6433,
      "epoch": 0.13618677042801555
    },
    {
      "step": 40,
      "loss": 1.6493,
      "epoch": 0.1556420233463035
    },
    {
      "step": 45,
      "loss": 1.6558,
      "epoch": 0.17509727626459143
    },
    {
      "step": 50,
      "loss": 1.6281,
      "epoch": 0.19455252918287938
    },
    {
      "step": 55,
      "loss": 1.6337,
      "epoch": 0.2140077821011673
    },
    {
      "step": 60,
      "loss": 1.5888,
      "epoch": 0.23346303501945526
    },
    {
      "step": 65,
      "loss": 1.5858,
      "epoch": 0.2529182879377432
    },
    {
      "step": 70,
      "loss": 1.5668,
      "epoch": 0.2723735408560311
    },
    {
      "step": 75,
      "loss": 1.5615,
      "epoch": 0.2918287937743191
    },
    {
      "step": 80,
      "loss": 1.5628,
      "epoch": 0.311284046692607
    },
    {
      "step": 85,
      "loss": 1.5592,
      "epoch": 0.33073929961089493
    },
    {
      "step": 90,
      "loss": 1.5178,
      "epoch": 0.35019455252918286
    },
    {
      "step": 95,
      "loss": 1.4996,
      "epoch": 0.36964980544747084
    },
    {
      "step": 100,
      "loss": 1.5195,
      "epoch": 0.38910505836575876
    },
    {
      "step": 105,
      "loss": 1.5287,
      "epoch": 0.4085603112840467
    },
    {
      "step": 110,
      "loss": 1.5269,
      "epoch": 0.4280155642023346
    },
    {
      "step": 115,
      "loss": 1.5649,
      "epoch": 0.4474708171206226
    },
    {
      "step": 120,
      "loss": 1.5043,
      "epoch": 0.4669260700389105
    },
    {
      "step": 125,
      "loss": 1.5102,
      "epoch": 0.48638132295719844
    },
    {
      "step": 130,
      "loss": 1.5325,
      "epoch": 0.5058365758754864
    },
    {
      "step": 135,
      "loss": 1.508,
      "epoch": 0.5252918287937743
    },
    {
      "step": 140,
      "loss": 1.4762,
      "epoch": 0.5447470817120622
    },
    {
      "step": 145,
      "loss": 1.4574,
      "epoch": 0.5642023346303502
    },
    {
      "step": 150,
      "loss": 1.4499,
      "epoch": 0.5836575875486382
    },
    {
      "step": 155,
      "loss": 1.4737,
      "epoch": 0.603112840466926
    },
    {
      "step": 160,
      "loss": 1.4787,
      "epoch": 0.622568093385214
    },
    {
      "step": 165,
      "loss": 1.4377,
      "epoch": 0.642023346303502
    },
    {
      "step": 170,
      "loss": 1.4949,
      "epoch": 0.6614785992217899
    },
    {
      "step": 175,
      "loss": 1.4887,
      "epoch": 0.6809338521400778
    },
    {
      "step": 180,
      "loss": 1.4592,
      "epoch": 0.7003891050583657
    },
    {
      "step": 185,
      "loss": 1.4364,
      "epoch": 0.7198443579766537
    },
    {
      "step": 190,
      "loss": 1.4833,
      "epoch": 0.7392996108949417
    },
    {
      "step": 195,
      "loss": 1.4595,
      "epoch": 0.7587548638132295
    },
    {
      "step": 200,
      "loss": 1.4448,
      "epoch": 0.7782101167315175
    },
    {
      "step": 205,
      "loss": 1.4249,
      "epoch": 0.7976653696498055
    },
    {
      "step": 210,
      "loss": 1.4547,
      "epoch": 0.8171206225680934
    },
    {
      "step": 215,
      "loss": 1.452,
      "epoch": 0.8365758754863813
    },
    {
      "step": 220,
      "loss": 1.4272,
      "epoch": 0.8560311284046692
    },
    {
      "step": 225,
      "loss": 1.4343,
      "epoch": 0.8754863813229572
    },
    {
      "step": 230,
      "loss": 1.4592,
      "epoch": 0.8949416342412452
    },
    {
      "step": 235,
      "loss": 1.4007,
      "epoch": 0.914396887159533
    },
    {
      "step": 240,
      "loss": 1.4604,
      "epoch": 0.933852140077821
    },
    {
      "step": 245,
      "loss": 1.4139,
      "epoch": 0.953307392996109
    },
    {
      "step": 250,
      "loss": 1.4223,
      "epoch": 0.9727626459143969
    },
    {
      "step": 255,
      "loss": 1.4128,
      "epoch": 0.9922178988326849
    }
  ],
  "train_runtime_s": 128.7839
}